{
"meta":{"test_sets":[],"test_metrics":[],"learn_metrics":[{"best_value":"Min","name":"MultiClass"}],"launch_mode":"Train","parameters":"","iteration_count":700,"learn_sets":["learn"],"name":"experiment"},
"iterations":[
{"learn":[1.751225825],"iteration":0,"passed_time":0.005239409646,"remaining_time":3.662347343},
{"learn":[1.715808739],"iteration":1,"passed_time":0.01032685572,"remaining_time":3.604072646},
{"learn":[1.68112896],"iteration":2,"passed_time":0.0159278754,"remaining_time":3.700576384},
{"learn":[1.649522577],"iteration":3,"passed_time":0.02134743809,"remaining_time":3.714454228},
{"learn":[1.613738373],"iteration":4,"passed_time":0.02731796545,"remaining_time":3.797197197},
{"learn":[1.583863766],"iteration":5,"passed_time":0.03283708581,"remaining_time":3.798156258},
{"learn":[1.556455888],"iteration":6,"passed_time":0.0385507149,"remaining_time":3.816520775},
{"learn":[1.533085515],"iteration":7,"passed_time":0.04485495778,"remaining_time":3.879953848},
{"learn":[1.51045871],"iteration":8,"passed_time":0.05048095752,"remaining_time":3.875815739},
{"learn":[1.486790597],"iteration":9,"passed_time":0.05681269869,"remaining_time":3.92007621},
{"learn":[1.466972091],"iteration":10,"passed_time":0.06356188653,"remaining_time":3.981285438},
{"learn":[1.448621521],"iteration":11,"passed_time":0.06946155038,"remaining_time":3.982462222},
{"learn":[1.426626292],"iteration":12,"passed_time":0.07467233511,"remaining_time":3.946145709},
{"learn":[1.407900296],"iteration":13,"passed_time":0.08030032878,"remaining_time":3.93471611},
{"learn":[1.390400659],"iteration":14,"passed_time":0.08520623262,"remaining_time":3.891084623},
{"learn":[1.375975534],"iteration":15,"passed_time":0.0894540935,"remaining_time":3.824162497},
{"learn":[1.362314784],"iteration":16,"passed_time":0.09453985782,"remaining_time":3.798277817},
{"learn":[1.346676713],"iteration":17,"passed_time":0.09874612048,"remaining_time":3.741380787},
{"learn":[1.333244717],"iteration":18,"passed_time":0.1036513219,"remaining_time":3.715081591},
{"learn":[1.32133884],"iteration":19,"passed_time":0.1091575954,"remaining_time":3.711358245},
{"learn":[1.306423743],"iteration":20,"passed_time":0.1142447514,"remaining_time":3.693913627},
{"learn":[1.296124343],"iteration":21,"passed_time":0.118652441,"remaining_time":3.656652501},
{"learn":[1.285843399],"iteration":22,"passed_time":0.1229304981,"remaining_time":3.618432488},
{"learn":[1.275353492],"iteration":23,"passed_time":0.1278404919,"remaining_time":3.600840521},
{"learn":[1.26672349],"iteration":24,"passed_time":0.1324583903,"remaining_time":3.576376539},
{"learn":[1.255372694],"iteration":25,"passed_time":0.1372708872,"remaining_time":3.558483767},
{"learn":[1.245817623],"iteration":26,"passed_time":0.1424822174,"remaining_time":3.551501197},
{"learn":[1.237059976],"iteration":27,"passed_time":0.1473619737,"remaining_time":3.536687369},
{"learn":[1.228716823],"iteration":28,"passed_time":0.1523420489,"remaining_time":3.524879822},
{"learn":[1.218002659],"iteration":29,"passed_time":0.1570280373,"remaining_time":3.5069595},
{"learn":[1.211135889],"iteration":30,"passed_time":0.1625108753,"remaining_time":3.507089534},
{"learn":[1.204178841],"iteration":31,"passed_time":0.1676990128,"remaining_time":3.500716893},
{"learn":[1.196576143],"iteration":32,"passed_time":0.1725486766,"remaining_time":3.487574766},
{"learn":[1.189446168],"iteration":33,"passed_time":0.178272736,"remaining_time":3.492048299},
{"learn":[1.184292261],"iteration":34,"passed_time":0.1833143938,"remaining_time":3.482973483},
{"learn":[1.17727513],"iteration":35,"passed_time":0.1891931467,"remaining_time":3.489562484},
{"learn":[1.171528734],"iteration":36,"passed_time":0.1949199496,"remaining_time":3.492754773},
{"learn":[1.16480505],"iteration":37,"passed_time":0.2005189053,"remaining_time":3.493250404},
{"learn":[1.160377477],"iteration":38,"passed_time":0.2057466508,"remaining_time":3.487141954},
{"learn":[1.153760932],"iteration":39,"passed_time":0.2110312423,"remaining_time":3.482015498},
{"learn":[1.150400714],"iteration":40,"passed_time":0.2168859356,"remaining_time":3.486044673},
{"learn":[1.147457222],"iteration":41,"passed_time":0.2229848137,"remaining_time":3.493428748},
{"learn":[1.14214398],"iteration":42,"passed_time":0.2283485613,"remaining_time":3.4889536},
{"learn":[1.137924895],"iteration":43,"passed_time":0.233754133,"remaining_time":3.485061619},
{"learn":[1.133996871],"iteration":44,"passed_time":0.2390846071,"remaining_time":3.480009281},
{"learn":[1.130892226],"iteration":45,"passed_time":0.2447178177,"remaining_time":3.479248973},
{"learn":[1.125443298],"iteration":46,"passed_time":0.249974315,"remaining_time":3.473047397},
{"learn":[1.122540263],"iteration":47,"passed_time":0.2544699506,"remaining_time":3.456550162},
{"learn":[1.118250477],"iteration":48,"passed_time":0.2600526363,"remaining_time":3.454985025},
{"learn":[1.114184213],"iteration":49,"passed_time":0.2645019843,"remaining_time":3.438525795},
{"learn":[1.111352268],"iteration":50,"passed_time":0.2692877072,"remaining_time":3.426818078},
{"learn":[1.106561048],"iteration":51,"passed_time":0.2740612653,"remaining_time":3.415224999},
{"learn":[1.104346737],"iteration":52,"passed_time":0.2789759717,"remaining_time":3.405612334},
{"learn":[1.102502398],"iteration":53,"passed_time":0.2837863674,"remaining_time":3.394925803},
{"learn":[1.099329177],"iteration":54,"passed_time":0.2906088893,"remaining_time":3.408049702},
{"learn":[1.096542806],"iteration":55,"passed_time":0.2969131999,"remaining_time":3.414501798},
{"learn":[1.093712179],"iteration":56,"passed_time":0.3021118057,"remaining_time":3.408033177},
{"learn":[1.091468099],"iteration":57,"passed_time":0.3079573379,"remaining_time":3.408769154},
{"learn":[1.086812077],"iteration":58,"passed_time":0.3133370021,"remaining_time":3.40422065},
{"learn":[1.083958758],"iteration":59,"passed_time":0.3183145951,"remaining_time":3.395355681},
{"learn":[1.082494475],"iteration":60,"passed_time":0.3232058963,"remaining_time":3.385714226},
{"learn":[1.080638546],"iteration":61,"passed_time":0.3284384882,"remaining_time":3.379737991},
{"learn":[1.078839909],"iteration":62,"passed_time":0.3333361834,"remaining_time":3.370399187},
{"learn":[1.077384087],"iteration":63,"passed_time":0.3387167109,"remaining_time":3.365997314},
{"learn":[1.074389035],"iteration":64,"passed_time":0.3443841063,"remaining_time":3.364367808},
{"learn":[1.072659485],"iteration":65,"passed_time":0.3495555317,"remaining_time":3.357851623},
{"learn":[1.069689457],"iteration":66,"passed_time":0.3551646315,"remaining_time":3.355510623},
{"learn":[1.065948817],"iteration":67,"passed_time":0.3610338875,"remaining_time":3.355491425},
{"learn":[1.06415813],"iteration":68,"passed_time":0.3655245339,"remaining_time":3.342695375},
{"learn":[1.062470371],"iteration":69,"passed_time":0.3708240221,"remaining_time":3.337416199},
{"learn":[1.058628141],"iteration":70,"passed_time":0.3759366104,"remaining_time":3.330480675},
{"learn":[1.055056047],"iteration":71,"passed_time":0.3806047431,"remaining_time":3.319719148},
{"learn":[1.053354808],"iteration":72,"passed_time":0.3849754928,"remaining_time":3.306570329},
{"learn":[1.051751959],"iteration":73,"passed_time":0.3912767812,"remaining_time":3.309990068},
{"learn":[1.050788251],"iteration":74,"passed_time":0.3969731114,"remaining_time":3.308109261},
{"learn":[1.049848239],"iteration":75,"passed_time":0.4012091132,"remaining_time":3.294137982},
{"learn":[1.047899936],"iteration":76,"passed_time":0.4062670474,"remaining_time":3.287069747},
{"learn":[1.045557274],"iteration":77,"passed_time":0.4108002626,"remaining_time":3.275868761},
{"learn":[1.043487871],"iteration":78,"passed_time":0.4152074,"remaining_time":3.263845511},
{"learn":[1.041817466],"iteration":79,"passed_time":0.420263873,"remaining_time":3.257045016},
{"learn":[1.040868388],"iteration":80,"passed_time":0.4246590476,"remaining_time":3.245233957},
{"learn":[1.039457761],"iteration":81,"passed_time":0.4292648621,"remaining_time":3.235191278},
{"learn":[1.038292459],"iteration":82,"passed_time":0.4333199532,"remaining_time":3.221185676},
{"learn":[1.036774138],"iteration":83,"passed_time":0.438924781,"remaining_time":3.218781728},
{"learn":[1.035979427],"iteration":84,"passed_time":0.4429869009,"remaining_time":3.205140518},
{"learn":[1.035128403],"iteration":85,"passed_time":0.4470825052,"remaining_time":3.191961142},
{"learn":[1.03414953],"iteration":86,"passed_time":0.45149131,"remaining_time":3.181197391},
{"learn":[1.033200467],"iteration":87,"passed_time":0.4573286883,"remaining_time":3.180513151},
{"learn":[1.031732245],"iteration":88,"passed_time":0.4622677152,"remaining_time":3.173545775},
{"learn":[1.030771142],"iteration":89,"passed_time":0.4664112229,"remaining_time":3.161231622},
{"learn":[1.029813539],"iteration":90,"passed_time":0.4716871207,"remaining_time":3.156675346},
{"learn":[1.028950914],"iteration":91,"passed_time":0.47622404,"remaining_time":3.147219743},
{"learn":[1.027914659],"iteration":92,"passed_time":0.4807848323,"remaining_time":3.138025733},
{"learn":[1.026634314],"iteration":93,"passed_time":0.4854641093,"remaining_time":3.129694152},
{"learn":[1.026083243],"iteration":94,"passed_time":0.4898437868,"remaining_time":3.119531485},
{"learn":[1.025273663],"iteration":95,"passed_time":0.4940148437,"remaining_time":3.108176725},
{"learn":[1.024304614],"iteration":96,"passed_time":0.4988381078,"remaining_time":3.101024526},
{"learn":[1.023312478],"iteration":97,"passed_time":0.5047112995,"remaining_time":3.100369411},
{"learn":[1.022480652],"iteration":98,"passed_time":0.5095269801,"remaining_time":3.093189041},
{"learn":[1.020595709],"iteration":99,"passed_time":0.515654682,"remaining_time":3.093928092},
{"learn":[1.019573137],"iteration":100,"passed_time":0.5227170502,"remaining_time":3.100074387},
{"learn":[1.018695659],"iteration":101,"passed_time":0.528394005,"remaining_time":3.097839363},
{"learn":[1.017950972],"iteration":102,"passed_time":0.5347253128,"remaining_time":3.099330211},
{"learn":[1.017284965],"iteration":103,"passed_time":0.5406434226,"remaining_time":3.098302691},
{"learn":[1.015961452],"iteration":104,"passed_time":0.5477112155,"remaining_time":3.103696888},
{"learn":[1.015381356],"iteration":105,"passed_time":0.5543359024,"remaining_time":3.106372887},
{"learn":[1.014731488],"iteration":106,"passed_time":0.559134533,"remaining_time":3.098754935},
{"learn":[1.014097832],"iteration":107,"passed_time":0.5637057396,"remaining_time":3.089942573},
{"learn":[1.013214207],"iteration":108,"passed_time":0.5702554611,"remaining_time":3.091935574},
{"learn":[1.012531791],"iteration":109,"passed_time":0.5759595052,"remaining_time":3.089237346},
{"learn":[1.011401166],"iteration":110,"passed_time":0.5810097739,"remaining_time":3.083015827},
{"learn":[1.010806999],"iteration":111,"passed_time":0.5865664731,"remaining_time":3.079473984},
{"learn":[1.010226712],"iteration":112,"passed_time":0.5910631565,"remaining_time":3.070390025},
{"learn":[1.009756485],"iteration":113,"passed_time":0.5955822669,"remaining_time":3.061501828},
{"learn":[1.009347765],"iteration":114,"passed_time":0.6010726487,"remaining_time":3.05763043},
{"learn":[1.008379254],"iteration":115,"passed_time":0.6059357848,"remaining_time":3.050573261},
{"learn":[1.007616667],"iteration":116,"passed_time":0.6103805582,"remaining_time":3.041468935},
{"learn":[1.006858255],"iteration":117,"passed_time":0.6150272525,"remaining_time":3.033439499},
{"learn":[1.006038346],"iteration":118,"passed_time":0.6206170858,"remaining_time":3.030071654},
{"learn":[1.005414236],"iteration":119,"passed_time":0.6251516566,"remaining_time":3.02156634},
{"learn":[1.004693569],"iteration":120,"passed_time":0.6309654753,"remaining_time":3.019248018},
{"learn":[1.00380227],"iteration":121,"passed_time":0.6367190633,"remaining_time":3.016587037},
{"learn":[1.00336793],"iteration":122,"passed_time":0.6418200173,"remaining_time":3.010814228},
{"learn":[1.002836921],"iteration":123,"passed_time":0.6476332093,"remaining_time":3.008360714},
{"learn":[1.00192708],"iteration":124,"passed_time":0.6541823321,"remaining_time":3.009238728},
{"learn":[1.000566159],"iteration":125,"passed_time":0.660490951,"remaining_time":3.008903221},
{"learn":[0.9998727402],"iteration":126,"passed_time":0.6679019876,"remaining_time":3.01344755},
{"learn":[0.9994854016],"iteration":127,"passed_time":0.6728317565,"remaining_time":3.006716912},
{"learn":[0.9987006865],"iteration":128,"passed_time":0.6779728699,"remaining_time":3.00094968},
{"learn":[0.9982941406],"iteration":129,"passed_time":0.6829566769,"remaining_time":2.994502352},
{"learn":[0.9979601769],"iteration":130,"passed_time":0.6881632964,"remaining_time":2.989045158},
{"learn":[0.9974361127],"iteration":131,"passed_time":0.6932476948,"remaining_time":2.983065838},
{"learn":[0.9968603183],"iteration":132,"passed_time":0.698687697,"remaining_time":2.978615971},
{"learn":[0.9966094558],"iteration":133,"passed_time":0.7034292579,"remaining_time":2.971201194},
{"learn":[0.9960050235],"iteration":134,"passed_time":0.7087225759,"remaining_time":2.966135225},
{"learn":[0.9955262836],"iteration":135,"passed_time":0.7133713802,"remaining_time":2.958393077},
{"learn":[0.9950938934],"iteration":136,"passed_time":0.7182897578,"remaining_time":2.951803895},
{"learn":[0.9946767104],"iteration":137,"passed_time":0.7227271879,"remaining_time":2.943280287},
{"learn":[0.9940612599],"iteration":138,"passed_time":0.7269402996,"remaining_time":2.93391013},
{"learn":[0.9934713127],"iteration":139,"passed_time":0.7324809332,"remaining_time":2.929923733},
{"learn":[0.9928563535],"iteration":140,"passed_time":0.7368596658,"remaining_time":2.921308888},
{"learn":[0.992512031],"iteration":141,"passed_time":0.7407419144,"remaining_time":2.910802734},
{"learn":[0.9918270086],"iteration":142,"passed_time":0.7451091781,"remaining_time":2.902278407},
{"learn":[0.9913339237],"iteration":143,"passed_time":0.7497153192,"remaining_time":2.894734149},
{"learn":[0.9908559185],"iteration":144,"passed_time":0.7542028206,"remaining_time":2.886776313},
{"learn":[0.9900063086],"iteration":145,"passed_time":0.7586703824,"remaining_time":2.878790355},
{"learn":[0.9894515442],"iteration":146,"passed_time":0.7637169414,"remaining_time":2.873030399},
{"learn":[0.988936304],"iteration":147,"passed_time":0.7686727806,"remaining_time":2.866941722},
{"learn":[0.9884237272],"iteration":148,"passed_time":0.7728682372,"remaining_time":2.858056367},
{"learn":[0.9880444317],"iteration":149,"passed_time":0.7785834131,"remaining_time":2.854805848},
{"learn":[0.9877111202],"iteration":150,"passed_time":0.783290796,"remaining_time":2.847858589},
{"learn":[0.9875069437],"iteration":151,"passed_time":0.787224967,"remaining_time":2.838153171},
{"learn":[0.9872505214],"iteration":152,"passed_time":0.7910415502,"remaining_time":2.828102797},
{"learn":[0.986773038],"iteration":153,"passed_time":0.795307725,"remaining_time":2.819727389},
{"learn":[0.9864303196],"iteration":154,"passed_time":0.7997163772,"remaining_time":2.811905972},
{"learn":[0.9859140133],"iteration":155,"passed_time":0.8043507906,"remaining_time":2.804915577},
{"learn":[0.9853869334],"iteration":156,"passed_time":0.8085308529,"remaining_time":2.796383778},
{"learn":[0.9847006399],"iteration":157,"passed_time":0.8136165488,"remaining_time":2.791013731},
{"learn":[0.9836196971],"iteration":158,"passed_time":0.8180197107,"remaining_time":2.783324928},
{"learn":[0.9834243415],"iteration":159,"passed_time":0.8220982883,"remaining_time":2.774581723},
{"learn":[0.9827822584],"iteration":160,"passed_time":0.8260642292,"remaining_time":2.765519376},
{"learn":[0.9821679766],"iteration":161,"passed_time":0.8311549419,"remaining_time":2.760255301},
{"learn":[0.981672445],"iteration":162,"passed_time":0.8351183462,"remaining_time":2.75127946},
{"learn":[0.9809154076],"iteration":163,"passed_time":0.8389788674,"remaining_time":2.742028493},
{"learn":[0.9804032157],"iteration":164,"passed_time":0.8428447319,"remaining_time":2.732860191},
{"learn":[0.9800518979],"iteration":165,"passed_time":0.8473181306,"remaining_time":2.725710131},
{"learn":[0.9795322265],"iteration":166,"passed_time":0.8513287195,"remaining_time":2.717115015},
{"learn":[0.9789009611],"iteration":167,"passed_time":0.8555515851,"remaining_time":2.709246686},
{"learn":[0.9785609239],"iteration":168,"passed_time":0.8600154936,"remaining_time":2.702178859},
{"learn":[0.9775563744],"iteration":169,"passed_time":0.8647803969,"remaining_time":2.696080061},
{"learn":[0.9767701894],"iteration":170,"passed_time":0.8697486818,"remaining_time":2.690626039},
{"learn":[0.9757437178],"iteration":171,"passed_time":0.8753588807,"remaining_time":2.687148192},
{"learn":[0.9752708422],"iteration":172,"passed_time":0.8810526102,"remaining_time":2.683900148},
{"learn":[0.9749743735],"iteration":173,"passed_time":0.8856561569,"remaining_time":2.677328382},
{"learn":[0.9746288154],"iteration":174,"passed_time":0.8905757605,"remaining_time":2.671727282},
{"learn":[0.9742908816],"iteration":175,"passed_time":0.8959035915,"remaining_time":2.667349329},
{"learn":[0.9738472681],"iteration":176,"passed_time":0.9002747134,"remaining_time":2.660133758},
{"learn":[0.9734621235],"iteration":177,"passed_time":0.9048082116,"remaining_time":2.653426328},
{"learn":[0.9730766425],"iteration":178,"passed_time":0.9097277603,"remaining_time":2.647866833},
{"learn":[0.9728087668],"iteration":179,"passed_time":0.9155817896,"remaining_time":2.645014059},
{"learn":[0.9724009238],"iteration":180,"passed_time":0.9200299305,"remaining_time":2.638096873},
{"learn":[0.972098443],"iteration":181,"passed_time":0.9253673073,"remaining_time":2.633737721},
{"learn":[0.9710891528],"iteration":182,"passed_time":0.9305706466,"remaining_time":2.628989204},
{"learn":[0.970207408],"iteration":183,"passed_time":0.9355943912,"remaining_time":2.623732097},
{"learn":[0.9691131369],"iteration":184,"passed_time":0.9406265862,"remaining_time":2.618501037},
{"learn":[0.9687403383],"iteration":185,"passed_time":0.9459068581,"remaining_time":2.613957662},
{"learn":[0.9682801572],"iteration":186,"passed_time":0.9512380966,"remaining_time":2.609546222},
{"learn":[0.9675033324],"iteration":187,"passed_time":0.9565618718,"remaining_time":2.605104672},
{"learn":[0.9670403419],"iteration":188,"passed_time":0.9625870363,"remaining_time":2.602550135},
{"learn":[0.9666390314],"iteration":189,"passed_time":0.967304488,"remaining_time":2.596448889},
{"learn":[0.9663161451],"iteration":190,"passed_time":0.9720377394,"remaining_time":2.590404238},
{"learn":[0.9656967068],"iteration":191,"passed_time":0.9785668173,"remaining_time":2.589124704},
{"learn":[0.9653328855],"iteration":192,"passed_time":0.9833453322,"remaining_time":2.583192142},
{"learn":[0.9647029349],"iteration":193,"passed_time":0.9890034192,"remaining_time":2.579565619},
{"learn":[0.9643241924],"iteration":194,"passed_time":0.9945123827,"remaining_time":2.575532068},
{"learn":[0.964056362],"iteration":195,"passed_time":0.9992816832,"remaining_time":2.569581471},
{"learn":[0.9631874504],"iteration":196,"passed_time":1.004599626,"remaining_time":2.565043715},
{"learn":[0.9627563866],"iteration":197,"passed_time":1.010345707,"remaining_time":2.56158356},
{"learn":[0.9618634864],"iteration":198,"passed_time":1.016331261,"remaining_time":2.558703325},
{"learn":[0.9611106211],"iteration":199,"passed_time":1.021427556,"remaining_time":2.553568889},
{"learn":[0.9604731371],"iteration":200,"passed_time":1.027870658,"remaining_time":2.551778401},
{"learn":[0.9602008279],"iteration":201,"passed_time":1.032303085,"remaining_time":2.544984834},
{"learn":[0.9598130864],"iteration":202,"passed_time":1.036246077,"remaining_time":2.537016257},
{"learn":[0.9594019712],"iteration":203,"passed_time":1.041479862,"remaining_time":2.532225547},
{"learn":[0.9590476577],"iteration":204,"passed_time":1.045665102,"remaining_time":2.524898661},
{"learn":[0.9586915211],"iteration":205,"passed_time":1.049884043,"remaining_time":2.517683093},
{"learn":[0.9584171397],"iteration":206,"passed_time":1.053602506,"remaining_time":2.509304519},
{"learn":[0.9580888737],"iteration":207,"passed_time":1.058619368,"remaining_time":2.504041967},
{"learn":[0.9573674933],"iteration":208,"passed_time":1.06287971,"remaining_time":2.497004487},
{"learn":[0.9569452217],"iteration":209,"passed_time":1.066916229,"remaining_time":2.489471201},
{"learn":[0.9564003824],"iteration":210,"passed_time":1.070730837,"remaining_time":2.481456774},
{"learn":[0.955839396],"iteration":211,"passed_time":1.075632419,"remaining_time":2.475984059},
{"learn":[0.9555359606],"iteration":212,"passed_time":1.079778234,"remaining_time":2.468788733},
{"learn":[0.954902523],"iteration":213,"passed_time":1.084060938,"remaining_time":2.461932785},
{"learn":[0.954671484],"iteration":214,"passed_time":1.088590139,"remaining_time":2.455656825},
{"learn":[0.9543499586],"iteration":215,"passed_time":1.093763888,"remaining_time":2.450841305},
{"learn":[0.9539630655],"iteration":216,"passed_time":1.098054253,"remaining_time":2.44405624},
{"learn":[0.953496223],"iteration":217,"passed_time":1.101745603,"remaining_time":2.435969636},
{"learn":[0.953008978],"iteration":218,"passed_time":1.106921385,"remaining_time":2.4311835},
{"learn":[0.9522474539],"iteration":219,"passed_time":1.111564547,"remaining_time":2.425231738},
{"learn":[0.9516782546],"iteration":220,"passed_time":1.115437653,"remaining_time":2.417622787},
{"learn":[0.9510999924],"iteration":221,"passed_time":1.119988021,"remaining_time":2.411505739},
{"learn":[0.9504562408],"iteration":222,"passed_time":1.125069354,"remaining_time":2.406538484},
{"learn":[0.9500540119],"iteration":223,"passed_time":1.129431001,"remaining_time":2.400040878},
{"learn":[0.9492391074],"iteration":224,"passed_time":1.133671721,"remaining_time":2.393306966},
{"learn":[0.9483083215],"iteration":225,"passed_time":1.138463199,"remaining_time":2.387750249},
{"learn":[0.947294622],"iteration":226,"passed_time":1.142860366,"remaining_time":2.381378647},
{"learn":[0.9469602914],"iteration":227,"passed_time":1.146957736,"remaining_time":2.374403735},
{"learn":[0.9465562373],"iteration":228,"passed_time":1.150982507,"remaining_time":2.367304632},
{"learn":[0.9461000169],"iteration":229,"passed_time":1.156155334,"remaining_time":2.362578292},
{"learn":[0.9457995592],"iteration":230,"passed_time":1.16036168,"remaining_time":2.355885836},
{"learn":[0.9455167258],"iteration":231,"passed_time":1.164551041,"remaining_time":2.349180548},
{"learn":[0.9451706536],"iteration":232,"passed_time":1.170295658,"remaining_time":2.345614043},
{"learn":[0.9447540748],"iteration":233,"passed_time":1.175355026,"remaining_time":2.340664283},
{"learn":[0.9438335092],"iteration":234,"passed_time":1.180062174,"remaining_time":2.335016642},
{"learn":[0.9434577895],"iteration":235,"passed_time":1.184460621,"remaining_time":2.328770035},
{"learn":[0.9429315326],"iteration":236,"passed_time":1.189360722,"remaining_time":2.323519048},
{"learn":[0.9426998133],"iteration":237,"passed_time":1.193417841,"remaining_time":2.316634633},
{"learn":[0.9423662615],"iteration":238,"passed_time":1.197415417,"remaining_time":2.309659027},
{"learn":[0.9420438733],"iteration":239,"passed_time":1.201381999,"remaining_time":2.302648832},
{"learn":[0.9418771131],"iteration":240,"passed_time":1.206140491,"remaining_time":2.297172138},
{"learn":[0.9414832027],"iteration":241,"passed_time":1.210017022,"remaining_time":2.290032215},
{"learn":[0.9406270236],"iteration":242,"passed_time":1.214306907,"remaining_time":2.283696529},
{"learn":[0.9403100781],"iteration":243,"passed_time":1.218012182,"remaining_time":2.276285061},
{"learn":[0.9400556687],"iteration":244,"passed_time":1.222633406,"remaining_time":2.270604897},
{"learn":[0.9395214686],"iteration":245,"passed_time":1.226883885,"remaining_time":2.264249121},
{"learn":[0.9389547327],"iteration":246,"passed_time":1.230743019,"remaining_time":2.257192663},
{"learn":[0.9385120365],"iteration":247,"passed_time":1.234582491,"remaining_time":2.250126152},
{"learn":[0.9383540251],"iteration":248,"passed_time":1.238765443,"remaining_time":2.24370769},
{"learn":[0.9382211566],"iteration":249,"passed_time":1.244817781,"remaining_time":2.240672006},
{"learn":[0.9376125905],"iteration":250,"passed_time":1.248854404,"remaining_time":2.234006483},
{"learn":[0.9368609778],"iteration":251,"passed_time":1.252834347,"remaining_time":2.227261061},
{"learn":[0.9363770947],"iteration":252,"passed_time":1.256931747,"remaining_time":2.220745024},
{"learn":[0.936049962],"iteration":253,"passed_time":1.260889552,"remaining_time":2.214002914},
{"learn":[0.9354768409],"iteration":254,"passed_time":1.265198396,"remaining_time":2.20789524},
{"learn":[0.9348379043],"iteration":255,"passed_time":1.269219237,"remaining_time":2.201302114},
{"learn":[0.9346610006],"iteration":256,"passed_time":1.272859463,"remaining_time":2.194072927},
{"learn":[0.9340394148],"iteration":257,"passed_time":1.277961175,"remaining_time":2.189375346},
{"learn":[0.9333345931],"iteration":258,"passed_time":1.283431907,"remaining_time":2.185302977},
{"learn":[0.9324493476],"iteration":259,"passed_time":1.28861581,"remaining_time":2.180734448},
{"learn":[0.932212571],"iteration":260,"passed_time":1.292340587,"remaining_time":2.173706964},
{"learn":[0.9319797158],"iteration":261,"passed_time":1.295924965,"remaining_time":2.16646998},
{"learn":[0.9314257791],"iteration":262,"passed_time":1.299668359,"remaining_time":2.159524993},
{"learn":[0.9310686258],"iteration":263,"passed_time":1.304148428,"remaining_time":2.153820889},
{"learn":[0.9305573026],"iteration":264,"passed_time":1.308935796,"remaining_time":2.148630457},
{"learn":[0.9303151339],"iteration":265,"passed_time":1.312610267,"remaining_time":2.141627278},
{"learn":[0.9300547424],"iteration":266,"passed_time":1.316382593,"remaining_time":2.134807726},
{"learn":[0.9296394731],"iteration":267,"passed_time":1.321067174,"remaining_time":2.129481416},
{"learn":[0.9292184379],"iteration":268,"passed_time":1.325063323,"remaining_time":2.123056849},
{"learn":[0.9287001105],"iteration":269,"passed_time":1.329084684,"remaining_time":2.116690422},
{"learn":[0.9285505393],"iteration":270,"passed_time":1.33293477,"remaining_time":2.110070171},
{"learn":[0.9281661106],"iteration":271,"passed_time":1.337295469,"remaining_time":2.104273752},
{"learn":[0.9278732218],"iteration":272,"passed_time":1.341441187,"remaining_time":2.098151601},
{"learn":[0.9277428225],"iteration":273,"passed_time":1.345244972,"remaining_time":2.091512256},
{"learn":[0.9275404035],"iteration":274,"passed_time":1.349841291,"remaining_time":2.086118359},
{"learn":[0.9271874029],"iteration":275,"passed_time":1.354425207,"remaining_time":2.080711188},
{"learn":[0.9266115138],"iteration":276,"passed_time":1.359105713,"remaining_time":2.075457461},
{"learn":[0.9260618634],"iteration":277,"passed_time":1.363428943,"remaining_time":2.069665518},
{"learn":[0.9257314836],"iteration":278,"passed_time":1.367934432,"remaining_time":2.064159125},
{"learn":[0.9252784926],"iteration":279,"passed_time":1.372106571,"remaining_time":2.058159857},
{"learn":[0.9250200747],"iteration":280,"passed_time":1.376303445,"remaining_time":2.052210476},
{"learn":[0.924682819],"iteration":281,"passed_time":1.379991813,"remaining_time":2.045519779},
{"learn":[0.9243478376],"iteration":282,"passed_time":1.384907173,"remaining_time":2.040658273},
{"learn":[0.9241520134],"iteration":283,"passed_time":1.388869869,"remaining_time":2.034400934},
{"learn":[0.9233823057],"iteration":284,"passed_time":1.393117191,"remaining_time":2.028574155},
{"learn":[0.9227949971],"iteration":285,"passed_time":1.397042476,"remaining_time":2.022292256},
{"learn":[0.9226111441],"iteration":286,"passed_time":1.401421584,"remaining_time":2.016679841},
{"learn":[0.9221239016],"iteration":287,"passed_time":1.405148991,"remaining_time":2.010143696},
{"learn":[0.9214517261],"iteration":288,"passed_time":1.409364901,"remaining_time":2.00432171},
{"learn":[0.9209915145],"iteration":289,"passed_time":1.413344895,"remaining_time":1.998177266},
{"learn":[0.9205196995],"iteration":290,"passed_time":1.418435226,"remaining_time":1.993608273},
{"learn":[0.9202548623],"iteration":291,"passed_time":1.422412349,"remaining_time":1.987480268},
{"learn":[0.9198074701],"iteration":292,"passed_time":1.427074383,"remaining_time":1.98231834},
{"learn":[0.9194557153],"iteration":293,"passed_time":1.43177533,"remaining_time":1.977213551},
{"learn":[0.9190270449],"iteration":294,"passed_time":1.436276596,"remaining_time":1.97183736},
{"learn":[0.918555622],"iteration":295,"passed_time":1.44124942,"remaining_time":1.967110695},
{"learn":[0.9179185753],"iteration":296,"passed_time":1.446011271,"remaining_time":1.962096102},
{"learn":[0.9174062086],"iteration":297,"passed_time":1.451363656,"remaining_time":1.957879831},
{"learn":[0.9169003951],"iteration":298,"passed_time":1.45627078,"remaining_time":1.953058805},
{"learn":[0.9165443808],"iteration":299,"passed_time":1.461074445,"remaining_time":1.94809926},
{"learn":[0.9161536032],"iteration":300,"passed_time":1.465547992,"remaining_time":1.942703152},
{"learn":[0.9155246253],"iteration":301,"passed_time":1.470841502,"remaining_time":1.938393768},
{"learn":[0.9152902924],"iteration":302,"passed_time":1.475542436,"remaining_time":1.933301476},
{"learn":[0.9146670933],"iteration":303,"passed_time":1.480526412,"remaining_time":1.928580458},
{"learn":[0.9141323581],"iteration":304,"passed_time":1.485804319,"remaining_time":1.92423838},
{"learn":[0.9138767788],"iteration":305,"passed_time":1.490311152,"remaining_time":1.918897365},
{"learn":[0.9134619728],"iteration":306,"passed_time":1.495257929,"remaining_time":1.914124971},
{"learn":[0.9127538997],"iteration":307,"passed_time":1.501085219,"remaining_time":1.910472097},
{"learn":[0.9123532464],"iteration":308,"passed_time":1.505803499,"remaining_time":1.905401839},
{"learn":[0.9121282899],"iteration":309,"passed_time":1.51047467,"remaining_time":1.900274585},
{"learn":[0.9116814866],"iteration":310,"passed_time":1.516156925,"remaining_time":1.896414932},
{"learn":[0.9114245991],"iteration":311,"passed_time":1.521512029,"remaining_time":1.892136754},
{"learn":[0.9110432618],"iteration":312,"passed_time":1.527286264,"remaining_time":1.888369918},
{"learn":[0.9107404177],"iteration":313,"passed_time":1.532977284,"remaining_time":1.884487999},
{"learn":[0.9099242068],"iteration":314,"passed_time":1.538017818,"remaining_time":1.879799556},
{"learn":[0.9093501711],"iteration":315,"passed_time":1.542325696,"remaining_time":1.874218567},
{"learn":[0.909114374],"iteration":316,"passed_time":1.546875833,"remaining_time":1.868938309},
{"learn":[0.9089049136],"iteration":317,"passed_time":1.552297717,"remaining_time":1.864709836},
{"learn":[0.9087665835],"iteration":318,"passed_time":1.557284559,"remaining_time":1.859954285},
{"learn":[0.9079095158],"iteration":319,"passed_time":1.562546776,"remaining_time":1.855524296},
{"learn":[0.9072584668],"iteration":320,"passed_time":1.567673474,"remaining_time":1.850929117},
{"learn":[0.906861281],"iteration":321,"passed_time":1.572429176,"remaining_time":1.84589512},
{"learn":[0.9064560513],"iteration":322,"passed_time":1.577079513,"remaining_time":1.840739865},
{"learn":[0.9062121386],"iteration":323,"passed_time":1.582948343,"remaining_time":1.837001781},
{"learn":[0.9056327296],"iteration":324,"passed_time":1.588166546,"remaining_time":1.832499861},
{"learn":[0.9052998957],"iteration":325,"passed_time":1.592876454,"remaining_time":1.82741041},
{"learn":[0.904856072],"iteration":326,"passed_time":1.598136608,"remaining_time":1.822950932},
{"learn":[0.9045346919],"iteration":327,"passed_time":1.602895127,"remaining_time":1.817917644},
{"learn":[0.9041691486],"iteration":328,"passed_time":1.607394689,"remaining_time":1.812594011},
{"learn":[0.9037719581],"iteration":329,"passed_time":1.612216757,"remaining_time":1.80763697},
{"learn":[0.9035358705],"iteration":330,"passed_time":1.616396248,"remaining_time":1.801964397},
{"learn":[0.9033094576],"iteration":331,"passed_time":1.620214663,"remaining_time":1.795900591},
{"learn":[0.9028070707],"iteration":332,"passed_time":1.624578279,"remaining_time":1.790451136},
{"learn":[0.9025143586],"iteration":333,"passed_time":1.62859215,"remaining_time":1.784624931},
{"learn":[0.902242128],"iteration":334,"passed_time":1.632604233,"remaining_time":1.778807598},
{"learn":[0.9019811997],"iteration":335,"passed_time":1.636325682,"remaining_time":1.772686155},
{"learn":[0.9014631067],"iteration":336,"passed_time":1.640620862,"remaining_time":1.767196952},
{"learn":[0.9012905306],"iteration":337,"passed_time":1.6450138,"remaining_time":1.761819513},
{"learn":[0.9009895688],"iteration":338,"passed_time":1.649082468,"remaining_time":1.756102569},
{"learn":[0.9006747841],"iteration":339,"passed_time":1.652729148,"remaining_time":1.74994851},
{"learn":[0.9002260925],"iteration":340,"passed_time":1.656586094,"remaining_time":1.744030521},
{"learn":[0.8996004109],"iteration":341,"passed_time":1.660890515,"remaining_time":1.738592996},
{"learn":[0.8989574919],"iteration":342,"passed_time":1.664907828,"remaining_time":1.73286325},
{"learn":[0.8985340945],"iteration":343,"passed_time":1.668733644,"remaining_time":1.726945283},
{"learn":[0.8982667234],"iteration":344,"passed_time":1.67270957,"remaining_time":1.721193906},
{"learn":[0.8979849086],"iteration":345,"passed_time":1.677222437,"remaining_time":1.716002147},
{"learn":[0.8977504978],"iteration":346,"passed_time":1.681453655,"remaining_time":1.710527782},
{"learn":[0.8974674754],"iteration":347,"passed_time":1.685239306,"remaining_time":1.704609873},
{"learn":[0.8966912841],"iteration":348,"passed_time":1.689397468,"remaining_time":1.699078829},
{"learn":[0.8963456997],"iteration":349,"passed_time":1.694402386,"remaining_time":1.694402386},
{"learn":[0.8955333634],"iteration":350,"passed_time":1.699310618,"remaining_time":1.689627937},
{"learn":[0.8953905081],"iteration":351,"passed_time":1.703120386,"remaining_time":1.683766746},
{"learn":[0.895024746],"iteration":352,"passed_time":1.706890549,"remaining_time":1.677878245},
{"learn":[0.8948035984],"iteration":353,"passed_time":1.711404815,"remaining_time":1.672729},
{"learn":[0.894518228],"iteration":354,"passed_time":1.715389957,"remaining_time":1.667069113},
{"learn":[0.8941619328],"iteration":355,"passed_time":1.719755735,"remaining_time":1.661786441},
{"learn":[0.8938445936],"iteration":356,"passed_time":1.723669738,"remaining_time":1.656074846},
{"learn":[0.8934683681],"iteration":357,"passed_time":1.728211978,"remaining_time":1.650973454},
{"learn":[0.8930991813],"iteration":358,"passed_time":1.732166967,"remaining_time":1.645317369},
{"learn":[0.892941346],"iteration":359,"passed_time":1.735700566,"remaining_time":1.639272756},
{"learn":[0.8924685828],"iteration":360,"passed_time":1.739683533,"remaining_time":1.633664037},
{"learn":[0.8920670687],"iteration":361,"passed_time":1.744131849,"remaining_time":1.628498798},
{"learn":[0.8918140548],"iteration":362,"passed_time":1.747693433,"remaining_time":1.622514289},
{"learn":[0.89146726],"iteration":363,"passed_time":1.751716072,"remaining_time":1.616968682},
{"learn":[0.8908358553],"iteration":364,"passed_time":1.756268738,"remaining_time":1.611917883},
{"learn":[0.890561842],"iteration":365,"passed_time":1.760259183,"remaining_time":1.606356741},
{"learn":[0.8901725961],"iteration":366,"passed_time":1.764401264,"remaining_time":1.600941746},
{"learn":[0.8898047592],"iteration":367,"passed_time":1.76872597,"remaining_time":1.59569843},
{"learn":[0.8892509202],"iteration":368,"passed_time":1.77342651,"remaining_time":1.590797221},
{"learn":[0.888862699],"iteration":369,"passed_time":1.778352132,"remaining_time":1.586097847},
{"learn":[0.8884175095],"iteration":370,"passed_time":1.782271131,"remaining_time":1.580504588},
{"learn":[0.8881497414],"iteration":371,"passed_time":1.786525618,"remaining_time":1.575216137},
{"learn":[0.8878896556],"iteration":372,"passed_time":1.790441311,"remaining_time":1.569636216},
{"learn":[0.8875492336],"iteration":373,"passed_time":1.795664783,"remaining_time":1.565205132},
{"learn":[0.8871783699],"iteration":374,"passed_time":1.799707171,"remaining_time":1.559746214},
{"learn":[0.8868738891],"iteration":375,"passed_time":1.803927827,"remaining_time":1.554448447},
{"learn":[0.8866168365],"iteration":376,"passed_time":1.807977766,"remaining_time":1.549010128},
{"learn":[0.8864287041],"iteration":377,"passed_time":1.811866389,"remaining_time":1.543441739},
{"learn":[0.8862550736],"iteration":378,"passed_time":1.815510125,"remaining_time":1.537674803},
{"learn":[0.8859699772],"iteration":379,"passed_time":1.819540949,"remaining_time":1.53224501},
{"learn":[0.8857266026],"iteration":380,"passed_time":1.823225689,"remaining_time":1.526532795},
{"learn":[0.8853260759],"iteration":381,"passed_time":1.827780599,"remaining_time":1.521555577},
{"learn":[0.8848010265],"iteration":382,"passed_time":1.832071818,"remaining_time":1.516362314},
{"learn":[0.8843203132],"iteration":383,"passed_time":1.836176851,"remaining_time":1.511020534},
{"learn":[0.8840822874],"iteration":384,"passed_time":1.840500898,"remaining_time":1.505864371},
{"learn":[0.8837752764],"iteration":385,"passed_time":1.844906678,"remaining_time":1.500779007},
{"learn":[0.883532512],"iteration":386,"passed_time":1.849347337,"remaining_time":1.495725366},
{"learn":[0.8833038014],"iteration":387,"passed_time":1.853365563,"remaining_time":1.490335195},
{"learn":[0.8829799491],"iteration":388,"passed_time":1.858357031,"remaining_time":1.485730171},
{"learn":[0.8825638609],"iteration":389,"passed_time":1.862838593,"remaining_time":1.480717856},
{"learn":[0.8821818967],"iteration":390,"passed_time":1.867123254,"remaining_time":1.475552649},
{"learn":[0.8817584986],"iteration":391,"passed_time":1.871473906,"remaining_time":1.470443783},
{"learn":[0.8814826137],"iteration":392,"passed_time":1.87607763,"remaining_time":1.465536469},
{"learn":[0.8810643775],"iteration":393,"passed_time":1.880353881,"remaining_time":1.460376365},
{"learn":[0.8807280207],"iteration":394,"passed_time":1.884459371,"remaining_time":1.455088881},
{"learn":[0.8804322143],"iteration":395,"passed_time":1.888568343,"remaining_time":1.449810041},
{"learn":[0.8802448553],"iteration":396,"passed_time":1.892805098,"remaining_time":1.444634621},
{"learn":[0.8800162545],"iteration":397,"passed_time":1.896935027,"remaining_time":1.43938286},
{"learn":[0.8797240884],"iteration":398,"passed_time":1.901136037,"remaining_time":1.434190344},
{"learn":[0.8795874738],"iteration":399,"passed_time":1.904835903,"remaining_time":1.428626927},
{"learn":[0.8791597719],"iteration":400,"passed_time":1.909850778,"remaining_time":1.424053323},
{"learn":[0.8788581927],"iteration":401,"passed_time":1.914069276,"remaining_time":1.418887175},
{"learn":[0.8785602261],"iteration":402,"passed_time":1.918063569,"remaining_time":1.413560496},
{"learn":[0.8783738332],"iteration":403,"passed_time":1.922230816,"remaining_time":1.408367132},
{"learn":[0.8782296519],"iteration":404,"passed_time":1.926430433,"remaining_time":1.403202414},
{"learn":[0.8781087908],"iteration":405,"passed_time":1.930250785,"remaining_time":1.39776781},
{"learn":[0.8777399661],"iteration":406,"passed_time":1.934533666,"remaining_time":1.392674113},
{"learn":[0.8773207775],"iteration":407,"passed_time":1.938574484,"remaining_time":1.38741115},
{"learn":[0.8769679639],"iteration":408,"passed_time":1.943768742,"remaining_time":1.382974826},
{"learn":[0.8765891312],"iteration":409,"passed_time":1.947972997,"remaining_time":1.377834559},
{"learn":[0.8762980009],"iteration":410,"passed_time":1.951938855,"remaining_time":1.372531214},
{"learn":[0.8761324081],"iteration":411,"passed_time":1.955844236,"remaining_time":1.367192087},
{"learn":[0.8757241747],"iteration":412,"passed_time":1.96010253,"remaining_time":1.362105148},
{"learn":[0.8755668292],"iteration":413,"passed_time":1.963568022,"remaining_time":1.356474527},
{"learn":[0.8753764246],"iteration":414,"passed_time":1.967133262,"remaining_time":1.350922843},
{"learn":[0.8750596671],"iteration":415,"passed_time":1.971024546,"remaining_time":1.345603296},
{"learn":[0.8747253796],"iteration":416,"passed_time":1.975505026,"remaining_time":1.340690461},
{"learn":[0.8742997414],"iteration":417,"passed_time":1.979405047,"remaining_time":1.335388094},
{"learn":[0.8738345466],"iteration":418,"passed_time":1.98380219,"remaining_time":1.330425812},
{"learn":[0.8735589072],"iteration":419,"passed_time":1.987849394,"remaining_time":1.325232929},
{"learn":[0.8731844909],"iteration":420,"passed_time":1.99250342,"remaining_time":1.320447635},
{"learn":[0.8729061065],"iteration":421,"passed_time":1.996181148,"remaining_time":1.315019808},
{"learn":[0.8726848154],"iteration":422,"passed_time":2.000180104,"remaining_time":1.309810612},
{"learn":[0.871985824],"iteration":423,"passed_time":2.004972348,"remaining_time":1.30512351},
{"learn":[0.871718702],"iteration":424,"passed_time":2.009724586,"remaining_time":1.300410026},
{"learn":[0.8713553075],"iteration":425,"passed_time":2.01415066,"remaining_time":1.295486574},
{"learn":[0.8711933939],"iteration":426,"passed_time":2.017699003,"remaining_time":1.290004281},
{"learn":[0.8708862882],"iteration":427,"passed_time":2.0223435,"remaining_time":1.285227645},
{"learn":[0.8705804163],"iteration":428,"passed_time":2.026372099,"remaining_time":1.280062561},
{"learn":[0.8702375305],"iteration":429,"passed_time":2.030261292,"remaining_time":1.27481523},
{"learn":[0.8701187564],"iteration":430,"passed_time":2.033970874,"remaining_time":1.2694621},
{"learn":[0.8697778373],"iteration":431,"passed_time":2.038665162,"remaining_time":1.264727462},
{"learn":[0.8695199413],"iteration":432,"passed_time":2.042685891,"remaining_time":1.259577674},
{"learn":[0.8693138652],"iteration":433,"passed_time":2.046750309,"remaining_time":1.254459867},
{"learn":[0.8690938704],"iteration":434,"passed_time":2.050537666,"remaining_time":1.249178118},
{"learn":[0.8684876843],"iteration":435,"passed_time":2.054974965,"remaining_time":1.244296768},
{"learn":[0.8682118283],"iteration":436,"passed_time":2.058571475,"remaining_time":1.238911437},
{"learn":[0.8676949919],"iteration":437,"passed_time":2.062742152,"remaining_time":1.233877726},
{"learn":[0.8672109591],"iteration":438,"passed_time":2.067546326,"remaining_time":1.229224581},
{"learn":[0.8670533877],"iteration":439,"passed_time":2.072516551,"remaining_time":1.224668871},
{"learn":[0.8669044325],"iteration":440,"passed_time":2.076275262,"remaining_time":1.219399757},
{"learn":[0.8667559776],"iteration":441,"passed_time":2.079800832,"remaining_time":1.21400139},
{"learn":[0.8664234886],"iteration":442,"passed_time":2.084015851,"remaining_time":1.209011453},
{"learn":[0.8662258771],"iteration":443,"passed_time":2.088330467,"remaining_time":1.204082431},
{"learn":[0.8658910155],"iteration":444,"passed_time":2.092267072,"remaining_time":1.198939558},
{"learn":[0.8656822021],"iteration":445,"passed_time":2.09579499,"remaining_time":1.193569344},
{"learn":[0.8654450539],"iteration":446,"passed_time":2.09938759,"remaining_time":1.188243983},
{"learn":[0.8651641884],"iteration":447,"passed_time":2.103614344,"remaining_time":1.183283069},
{"learn":[0.8648798453],"iteration":448,"passed_time":2.107673703,"remaining_time":1.178231847},
{"learn":[0.8645922658],"iteration":449,"passed_time":2.111482878,"remaining_time":1.173046043},
{"learn":[0.8643973251],"iteration":450,"passed_time":2.115292991,"remaining_time":1.167866862},
{"learn":[0.8639290921],"iteration":451,"passed_time":2.120006501,"remaining_time":1.163189408},
{"learn":[0.8635317335],"iteration":452,"passed_time":2.125163096,"remaining_time":1.158753388},
{"learn":[0.8632186938],"iteration":453,"passed_time":2.129846113,"remaining_time":1.154057586},
{"learn":[0.8628355016],"iteration":454,"passed_time":2.134281312,"remaining_time":1.149228399},
{"learn":[0.862240881],"iteration":455,"passed_time":2.139096731,"remaining_time":1.144604391},
{"learn":[0.8619768864],"iteration":456,"passed_time":2.142904473,"remaining_time":1.139443735},
{"learn":[0.8617761586],"iteration":457,"passed_time":2.146909215,"remaining_time":1.134393079},
{"learn":[0.8615396258],"iteration":458,"passed_time":2.150941386,"remaining_time":1.129361382},
{"learn":[0.8612351463],"iteration":459,"passed_time":2.155068404,"remaining_time":1.124383515},
{"learn":[0.8608119688],"iteration":460,"passed_time":2.159333532,"remaining_time":1.119480942},
{"learn":[0.8605051344],"iteration":461,"passed_time":2.163239727,"remaining_time":1.114396223},
{"learn":[0.8601414291],"iteration":462,"passed_time":2.167352427,"remaining_time":1.109422301},
{"learn":[0.8599733765],"iteration":463,"passed_time":2.171345027,"remaining_time":1.104391005},
{"learn":[0.8596715609],"iteration":464,"passed_time":2.175211873,"remaining_time":1.099300624},
{"learn":[0.8593928695],"iteration":465,"passed_time":2.17930284,"remaining_time":1.094328036},
{"learn":[0.8592268922],"iteration":466,"passed_time":2.183333556,"remaining_time":1.089329162},
{"learn":[0.8589025183],"iteration":467,"passed_time":2.187838458,"remaining_time":1.084569492},
{"learn":[0.8586082348],"iteration":468,"passed_time":2.191569824,"remaining_time":1.079429914},
{"learn":[0.858379383],"iteration":469,"passed_time":2.195429848,"remaining_time":1.074359287},
{"learn":[0.8581376442],"iteration":470,"passed_time":2.199688993,"remaining_time":1.069487854},
{"learn":[0.8577356616],"iteration":471,"passed_time":2.204460913,"remaining_time":1.064866712},
{"learn":[0.8575280606],"iteration":472,"passed_time":2.208338167,"remaining_time":1.059815569},
{"learn":[0.8572599046],"iteration":473,"passed_time":2.212656526,"remaining_time":1.054979694},
{"learn":[0.8569580703],"iteration":474,"passed_time":2.217990997,"remaining_time":1.050627314},
{"learn":[0.8566489567],"iteration":475,"passed_time":2.222484145,"remaining_time":1.045874892},
{"learn":[0.856451886],"iteration":476,"passed_time":2.226469675,"remaining_time":1.040886242},
{"learn":[0.856106864],"iteration":477,"passed_time":2.231631849,"remaining_time":1.036448265},
{"learn":[0.8558510216],"iteration":478,"passed_time":2.23671655,"remaining_time":1.031971519},
{"learn":[0.8556385889],"iteration":479,"passed_time":2.240379198,"remaining_time":1.026840466},
{"learn":[0.855486812],"iteration":480,"passed_time":2.244257075,"remaining_time":1.021813512},
{"learn":[0.8553149156],"iteration":481,"passed_time":2.248079629,"remaining_time":1.016766305},
{"learn":[0.8551695111],"iteration":482,"passed_time":2.252235154,"remaining_time":1.011873765},
{"learn":[0.8548678687],"iteration":483,"passed_time":2.256171602,"remaining_time":1.0068865},
{"learn":[0.8545370017],"iteration":484,"passed_time":2.260195473,"remaining_time":1.001942323},
{"learn":[0.8542286601],"iteration":485,"passed_time":2.264672617,"remaining_time":0.9972015229},
{"learn":[0.8541597573],"iteration":486,"passed_time":2.269563654,"remaining_time":0.99264283},
{"learn":[0.8540920123],"iteration":487,"passed_time":2.273308687,"remaining_time":0.9875849216},
{"learn":[0.8537739426],"iteration":488,"passed_time":2.277512622,"remaining_time":0.9827303951},
{"learn":[0.8534465831],"iteration":489,"passed_time":2.282131156,"remaining_time":0.9780562098},
{"learn":[0.8533445771],"iteration":490,"passed_time":2.286572398,"remaining_time":0.9733067844},
{"learn":[0.8524938246],"iteration":491,"passed_time":2.291304492,"remaining_time":0.9686815737},
{"learn":[0.8521867544],"iteration":492,"passed_time":2.295264362,"remaining_time":0.9637316895},
{"learn":[0.8518382993],"iteration":493,"passed_time":2.299196036,"remaining_time":0.9587740553},
{"learn":[0.8517620838],"iteration":494,"passed_time":2.302804804,"remaining_time":0.9536868381},
{"learn":[0.8514523219],"iteration":495,"passed_time":2.306995613,"remaining_time":0.9488449698},
{"learn":[0.851231367],"iteration":496,"passed_time":2.310997119,"remaining_time":0.9439284006},
{"learn":[0.85094749],"iteration":497,"passed_time":2.315528537,"remaining_time":0.9392304507},
{"learn":[0.8508331525],"iteration":498,"passed_time":2.319207936,"remaining_time":0.9341899701},
{"learn":[0.8505638967],"iteration":499,"passed_time":2.323343097,"remaining_time":0.929337239},
{"learn":[0.8504213341],"iteration":500,"passed_time":2.327110423,"remaining_time":0.9243412658},
{"learn":[0.8502667154],"iteration":501,"passed_time":2.331130802,"remaining_time":0.9194499975},
{"learn":[0.8501156151],"iteration":502,"passed_time":2.335397468,"remaining_time":0.9146586503},
{"learn":[0.8496647698],"iteration":503,"passed_time":2.340586439,"remaining_time":0.9102280595},
{"learn":[0.8494840038],"iteration":504,"passed_time":2.345477998,"remaining_time":0.9056796229},
{"learn":[0.8492993222],"iteration":505,"passed_time":2.349935913,"remaining_time":0.9009635714},
{"learn":[0.8489726327],"iteration":506,"passed_time":2.354642955,"remaining_time":0.8963433733},
{"learn":[0.8486720984],"iteration":507,"passed_time":2.359525956,"remaining_time":0.8917893377},
{"learn":[0.8483239912],"iteration":508,"passed_time":2.364548758,"remaining_time":0.8872864692},
{"learn":[0.8480623141],"iteration":509,"passed_time":2.369535516,"remaining_time":0.8827681332},
{"learn":[0.8479156933],"iteration":510,"passed_time":2.373976843,"remaining_time":0.8780462297},
{"learn":[0.8476758664],"iteration":511,"passed_time":2.3784139,"remaining_time":0.8733238539},
{"learn":[0.8472746093],"iteration":512,"passed_time":2.384050043,"remaining_time":0.8690396845},
{"learn":[0.8471306423],"iteration":513,"passed_time":2.388330899,"remaining_time":0.8642598193},
{"learn":[0.8468912079],"iteration":514,"passed_time":2.392577417,"remaining_time":0.8594695577},
{"learn":[0.8465502406],"iteration":515,"passed_time":2.397387587,"remaining_time":0.8548823954},
{"learn":[0.8463076823],"iteration":516,"passed_time":2.401836913,"remaining_time":0.8501666444},
{"learn":[0.8462075753],"iteration":517,"passed_time":2.406145745,"remaining_time":0.845402559},
{"learn":[0.8459497102],"iteration":518,"passed_time":2.410991898,"remaining_time":0.8408276174},
{"learn":[0.8457059527],"iteration":519,"passed_time":2.416021821,"remaining_time":0.8363152458},
{"learn":[0.8456054898],"iteration":520,"passed_time":2.420518465,"remaining_time":0.8316176682},
{"learn":[0.8452869376],"iteration":521,"passed_time":2.425087658,"remaining_time":0.8269455997},
{"learn":[0.8451792931],"iteration":522,"passed_time":2.429811376,"remaining_time":0.822326221},
{"learn":[0.844754237],"iteration":523,"passed_time":2.435218462,"remaining_time":0.8179359719},
{"learn":[0.8446321648],"iteration":524,"passed_time":2.439576213,"remaining_time":0.813192071},
{"learn":[0.8444368212],"iteration":525,"passed_time":2.443890315,"remaining_time":0.8084351994},
{"learn":[0.8443069188],"iteration":526,"passed_time":2.449058001,"remaining_time":0.8039602167},
{"learn":[0.8438922258],"iteration":527,"passed_time":2.454586846,"remaining_time":0.7996002604},
{"learn":[0.8438219191],"iteration":528,"passed_time":2.458671307,"remaining_time":0.7947689859},
{"learn":[0.8433924974],"iteration":529,"passed_time":2.463927833,"remaining_time":0.7903164748},
{"learn":[0.8431795132],"iteration":530,"passed_time":2.468346942,"remaining_time":0.7855944129},
{"learn":[0.8429455573],"iteration":531,"passed_time":2.4733728,"remaining_time":0.7810650948},
{"learn":[0.8426812876],"iteration":532,"passed_time":2.47889542,"remaining_time":0.7766895594},
{"learn":[0.8424361942],"iteration":533,"passed_time":2.483473184,"remaining_time":0.7720160085},
{"learn":[0.8421940655],"iteration":534,"passed_time":2.488289958,"remaining_time":0.7674165291},
{"learn":[0.8418078395],"iteration":535,"passed_time":2.493328263,"remaining_time":0.7628840207},
{"learn":[0.8414648648],"iteration":536,"passed_time":2.498996957,"remaining_time":0.7585409759},
{"learn":[0.841024056],"iteration":537,"passed_time":2.503425887,"remaining_time":0.7538196909},
{"learn":[0.840662931],"iteration":538,"passed_time":2.507714356,"remaining_time":0.7490575348},
{"learn":[0.8405221866],"iteration":539,"passed_time":2.512239019,"remaining_time":0.7443671168},
{"learn":[0.8402797397],"iteration":540,"passed_time":2.51656655,"remaining_time":0.7396193742},
{"learn":[0.8401775311],"iteration":541,"passed_time":2.520317119,"remaining_time":0.7347049904},
{"learn":[0.8399206548],"iteration":542,"passed_time":2.52494764,"remaining_time":0.7300493176},
{"learn":[0.8394979541],"iteration":543,"passed_time":2.530513043,"remaining_time":0.7256618285},
{"learn":[0.8390952043],"iteration":544,"passed_time":2.534999845,"remaining_time":0.7209632586},
{"learn":[0.8388834128],"iteration":545,"passed_time":2.539197505,"remaining_time":0.7161839115},
{"learn":[0.8386638718],"iteration":546,"passed_time":2.543699066,"remaining_time":0.7114916947},
{"learn":[0.8385426869],"iteration":547,"passed_time":2.547551169,"remaining_time":0.7066200322},
{"learn":[0.8383915129],"iteration":548,"passed_time":2.551233182,"remaining_time":0.7017053015},
{"learn":[0.8381537391],"iteration":549,"passed_time":2.555377224,"remaining_time":0.696921061},
{"learn":[0.8379960452],"iteration":550,"passed_time":2.559204277,"remaining_time":0.692053425},
{"learn":[0.8373547074],"iteration":551,"passed_time":2.56462148,"remaining_time":0.6876159041},
{"learn":[0.8370939273],"iteration":552,"passed_time":2.569012036,"remaining_time":0.6829019337},
{"learn":[0.8369339203],"iteration":553,"passed_time":2.573296618,"remaining_time":0.6781612026},
{"learn":[0.8367374034],"iteration":554,"passed_time":2.57811919,"remaining_time":0.6735626712},
{"learn":[0.8365907668],"iteration":555,"passed_time":2.582541915,"remaining_time":0.6688597765},
{"learn":[0.8365493631],"iteration":556,"passed_time":2.586684116,"remaining_time":0.6640858683},
{"learn":[0.836294346],"iteration":557,"passed_time":2.591333424,"remaining_time":0.6594432727},
{"learn":[0.8361529866],"iteration":558,"passed_time":2.596192743,"remaining_time":0.6548536257},
{"learn":[0.8359809457],"iteration":559,"passed_time":2.600365294,"remaining_time":0.6500913234},
{"learn":[0.8358499346],"iteration":560,"passed_time":2.604407374,"remaining_time":0.6452987968},
{"learn":[0.8356841504],"iteration":561,"passed_time":2.608659669,"remaining_time":0.6405605592},
{"learn":[0.8353983673],"iteration":562,"passed_time":2.613126176,"remaining_time":0.6358761743},
{"learn":[0.8350774476],"iteration":563,"passed_time":2.616945441,"remaining_time":0.6310364893},
{"learn":[0.8348275983],"iteration":564,"passed_time":2.622015589,"remaining_time":0.6264993},
{"learn":[0.834498272],"iteration":565,"passed_time":2.627240036,"remaining_time":0.6219967576},
{"learn":[0.8341802524],"iteration":566,"passed_time":2.632777452,"remaining_time":0.6175650813},
{"learn":[0.8339589232],"iteration":567,"passed_time":2.638714181,"remaining_time":0.6132223097},
{"learn":[0.8337183953],"iteration":568,"passed_time":2.644833001,"remaining_time":0.6089158578},
{"learn":[0.8333038474],"iteration":569,"passed_time":2.650187174,"remaining_time":0.6044286537},
{"learn":[0.8330764802],"iteration":570,"passed_time":2.65593147,"remaining_time":0.6000265493},
{"learn":[0.832876117],"iteration":571,"passed_time":2.66228223,"remaining_time":0.595755464},
{"learn":[0.8327236913],"iteration":572,"passed_time":2.666805228,"remaining_time":0.5910720139},
{"learn":[0.8324514871],"iteration":573,"passed_time":2.673032282,"remaining_time":0.5867631838},
{"learn":[0.8321314566],"iteration":574,"passed_time":2.679568273,"remaining_time":0.5825148419},
{"learn":[0.8319683929],"iteration":575,"passed_time":2.68462956,"remaining_time":0.5779410859},
{"learn":[0.831564712],"iteration":576,"passed_time":2.689926544,"remaining_time":0.5734158837},
{"learn":[0.8311910615],"iteration":577,"passed_time":2.695674295,"remaining_time":0.5689831556},
{"learn":[0.8309147921],"iteration":578,"passed_time":2.699679766,"remaining_time":0.5641817819},
{"learn":[0.8306802875],"iteration":579,"passed_time":2.703839623,"remaining_time":0.5594150945},
{"learn":[0.8303481445],"iteration":580,"passed_time":2.7092153,"remaining_time":0.5548995193},
{"learn":[0.8302531102],"iteration":581,"passed_time":2.713154988,"remaining_time":0.5500898429},
{"learn":[0.8299590843],"iteration":582,"passed_time":2.717437786,"remaining_time":0.5453520086},
{"learn":[0.8298589722],"iteration":583,"passed_time":2.721608388,"remaining_time":0.5405934469},
{"learn":[0.8296971655],"iteration":584,"passed_time":2.727373356,"remaining_time":0.5361503179},
{"learn":[0.8295275129],"iteration":585,"passed_time":2.732325612,"remaining_time":0.531544573},
{"learn":[0.8293526995],"iteration":586,"passed_time":2.736441167,"remaining_time":0.526776579},
{"learn":[0.8292493992],"iteration":587,"passed_time":2.740256173,"remaining_time":0.5219535568},
{"learn":[0.8290317313],"iteration":588,"passed_time":2.744300228,"remaining_time":0.5171771227},
{"learn":[0.8288910729],"iteration":589,"passed_time":2.748139586,"remaining_time":0.5123650076},
{"learn":[0.8287881433],"iteration":590,"passed_time":2.751638115,"remaining_time":0.5074933242},
{"learn":[0.8284121989],"iteration":591,"passed_time":2.756184648,"remaining_time":0.5028174696},
{"learn":[0.8281461698],"iteration":592,"passed_time":2.760402227,"remaining_time":0.4980826953},
{"learn":[0.8279954896],"iteration":593,"passed_time":2.764121574,"remaining_time":0.4932607523},
{"learn":[0.8278157064],"iteration":594,"passed_time":2.767811573,"remaining_time":0.4884373365},
{"learn":[0.8277539528],"iteration":595,"passed_time":2.771457948,"remaining_time":0.4836101118},
{"learn":[0.8273502377],"iteration":596,"passed_time":2.776651357,"remaining_time":0.4790537517},
{"learn":[0.8270254084],"iteration":597,"passed_time":2.780759951,"remaining_time":0.4743102258},
{"learn":[0.8269020549],"iteration":598,"passed_time":2.784447721,"remaining_time":0.4694978628},
{"learn":[0.8268082708],"iteration":599,"passed_time":2.788277917,"remaining_time":0.4647129862},
{"learn":[0.8265368174],"iteration":600,"passed_time":2.792987578,"remaining_time":0.4600761568},
{"learn":[0.8261900293],"iteration":601,"passed_time":2.797141833,"remaining_time":0.4553486705},
{"learn":[0.8259763404],"iteration":602,"passed_time":2.801215319,"remaining_time":0.4506100928},
{"learn":[0.8257925264],"iteration":603,"passed_time":2.805714934,"remaining_time":0.4459414465},
{"learn":[0.8255311679],"iteration":604,"passed_time":2.810050893,"remaining_time":0.441247661},
{"learn":[0.8251255323],"iteration":605,"passed_time":2.814346472,"remaining_time":0.4365487928},
{"learn":[0.8247781295],"iteration":606,"passed_time":2.818855917,"remaining_time":0.4318840202},
{"learn":[0.8244781465],"iteration":607,"passed_time":2.824783402,"remaining_time":0.4274343306},
{"learn":[0.8242405061],"iteration":608,"passed_time":2.828608963,"remaining_time":0.4226657071},
{"learn":[0.8241139412],"iteration":609,"passed_time":2.832502824,"remaining_time":0.4179102527},
{"learn":[0.8240294744],"iteration":610,"passed_time":2.836222161,"remaining_time":0.4131321969},
{"learn":[0.8235437867],"iteration":611,"passed_time":2.841068398,"remaining_time":0.4085196389},
{"learn":[0.823242534],"iteration":612,"passed_time":2.845417681,"remaining_time":0.4038357883},
{"learn":[0.8230349724],"iteration":613,"passed_time":2.849555341,"remaining_time":0.3991233866},
{"learn":[0.8229174504],"iteration":614,"passed_time":2.853475904,"remaining_time":0.3943828485},
{"learn":[0.8227488972],"iteration":615,"passed_time":2.857974932,"remaining_time":0.3897238544},
{"learn":[0.8225676891],"iteration":616,"passed_time":2.861742253,"remaining_time":0.3849669481},
{"learn":[0.8224131719],"iteration":617,"passed_time":2.866048589,"remaining_time":0.3802847642},
{"learn":[0.8222129019],"iteration":618,"passed_time":2.870065286,"remaining_time":0.3755658937},
{"learn":[0.8218797332],"iteration":619,"passed_time":2.874888324,"remaining_time":0.3709533322},
{"learn":[0.8216636154],"iteration":620,"passed_time":2.878960934,"remaining_time":0.3662446277},
{"learn":[0.8215459576],"iteration":621,"passed_time":2.882984951,"remaining_time":0.3615318749},
{"learn":[0.8214426588],"iteration":622,"passed_time":2.887264012,"remaining_time":0.3568528554},
{"learn":[0.8213517301],"iteration":623,"passed_time":2.89122977,"remaining_time":0.3521369592},
{"learn":[0.8211272391],"iteration":624,"passed_time":2.895414506,"remaining_time":0.3474497407},
{"learn":[0.8209598444],"iteration":625,"passed_time":2.89940098,"remaining_time":0.3427406909},
{"learn":[0.8208490021],"iteration":626,"passed_time":2.903323702,"remaining_time":0.3380265235},
{"learn":[0.8205036522],"iteration":627,"passed_time":2.908009732,"remaining_time":0.3334023896},
{"learn":[0.8203893347],"iteration":628,"passed_time":2.911938456,"remaining_time":0.3286925761},
{"learn":[0.8202272467],"iteration":629,"passed_time":2.916191065,"remaining_time":0.3240212294},
{"learn":[0.8200491998],"iteration":630,"passed_time":2.92041663,"remaining_time":0.3193482527},
{"learn":[0.8198318697],"iteration":631,"passed_time":2.924509554,"remaining_time":0.3146624204},
{"learn":[0.8196857496],"iteration":632,"passed_time":2.928245788,"remaining_time":0.3099407075},
{"learn":[0.8192767222],"iteration":633,"passed_time":2.931978146,"remaining_time":0.3052216998},
{"learn":[0.8191539685],"iteration":634,"passed_time":2.935952224,"remaining_time":0.3005305426},
{"learn":[0.8189935046],"iteration":635,"passed_time":2.940129116,"remaining_time":0.2958620494},
{"learn":[0.8187592774],"iteration":636,"passed_time":2.944203663,"remaining_time":0.2911849776},
{"learn":[0.8187215323],"iteration":637,"passed_time":2.947934018,"remaining_time":0.2864763466},
{"learn":[0.8183999694],"iteration":638,"passed_time":2.952551715,"remaining_time":0.2818554845},
{"learn":[0.818186953],"iteration":639,"passed_time":2.957558297,"remaining_time":0.2772710904},
{"learn":[0.8181428578],"iteration":640,"passed_time":2.961247046,"remaining_time":0.2725640807},
{"learn":[0.8178075372],"iteration":641,"passed_time":2.965476287,"remaining_time":0.2679090726},
{"learn":[0.8176622424],"iteration":642,"passed_time":2.969967911,"remaining_time":0.2632786484},
{"learn":[0.8175861882],"iteration":643,"passed_time":2.974010196,"remaining_time":0.2586095822},
{"learn":[0.8174393686],"iteration":644,"passed_time":2.978017393,"remaining_time":0.2539394676},
{"learn":[0.817194373],"iteration":645,"passed_time":2.982030536,"remaining_time":0.2492719024},
{"learn":[0.8170688803],"iteration":646,"passed_time":2.985851842,"remaining_time":0.2445906455},
{"learn":[0.8168072788],"iteration":647,"passed_time":2.989832891,"remaining_time":0.2399248617},
{"learn":[0.8164242756],"iteration":648,"passed_time":2.994259438,"remaining_time":0.2352961962},
{"learn":[0.8161900412],"iteration":649,"passed_time":2.998354972,"remaining_time":0.2306426902},
{"learn":[0.8156836606],"iteration":650,"passed_time":3.002945974,"remaining_time":0.2260281916},
{"learn":[0.8155009356],"iteration":651,"passed_time":3.006904645,"remaining_time":0.2213672132},
{"learn":[0.8150759908],"iteration":652,"passed_time":3.011152224,"remaining_time":0.21672918},
{"learn":[0.8146039702],"iteration":653,"passed_time":3.015560418,"remaining_time":0.212103638},
{"learn":[0.814278611],"iteration":654,"passed_time":3.02030443,"remaining_time":0.2075018311},
{"learn":[0.8140480892],"iteration":655,"passed_time":3.024463267,"remaining_time":0.2028603411},
{"learn":[0.8140009651],"iteration":656,"passed_time":3.028423121,"remaining_time":0.1982072971},
{"learn":[0.8137687152],"iteration":657,"passed_time":3.032566972,"remaining_time":0.1935681046},
{"learn":[0.8135102551],"iteration":658,"passed_time":3.037202531,"remaining_time":0.1889610073},
{"learn":[0.8134039002],"iteration":659,"passed_time":3.040939018,"remaining_time":0.1842993344},
{"learn":[0.8130207155],"iteration":660,"passed_time":3.044808854,"remaining_time":0.1796483287},
{"learn":[0.8127233775],"iteration":661,"passed_time":3.048931908,"remaining_time":0.1750142183},
{"learn":[0.8125972631],"iteration":662,"passed_time":3.054127687,"remaining_time":0.170441515},
{"learn":[0.8124397816],"iteration":663,"passed_time":3.058344031,"remaining_time":0.165813833},
{"learn":[0.8122645059],"iteration":664,"passed_time":3.062279672,"remaining_time":0.1611726143},
{"learn":[0.8120606298],"iteration":665,"passed_time":3.066437401,"remaining_time":0.1565448523},
{"learn":[0.8118293664],"iteration":666,"passed_time":3.070856059,"remaining_time":0.1519314092},
{"learn":[0.8116214417],"iteration":667,"passed_time":3.075162425,"remaining_time":0.14731317},
{"learn":[0.8115331147],"iteration":668,"passed_time":3.079103129,"remaining_time":0.1426789193},
{"learn":[0.8114737812],"iteration":669,"passed_time":3.082745012,"remaining_time":0.1380333587},
{"learn":[0.8112778631],"iteration":670,"passed_time":3.086965951,"remaining_time":0.1334158161},
{"learn":[0.810919659],"iteration":671,"passed_time":3.090980531,"remaining_time":0.1287908554},
{"learn":[0.8106599652],"iteration":672,"passed_time":3.095309128,"remaining_time":0.1241803068},
{"learn":[0.8104519705],"iteration":673,"passed_time":3.099324129,"remaining_time":0.1195584975},
{"learn":[0.8102609174],"iteration":674,"passed_time":3.103622917,"remaining_time":0.1149489969},
{"learn":[0.8099590981],"iteration":675,"passed_time":3.110420204,"remaining_time":0.1104291197},
{"learn":[0.8098393477],"iteration":676,"passed_time":3.113933528,"remaining_time":0.1057909471},
{"learn":[0.8095347568],"iteration":677,"passed_time":3.11946391,"remaining_time":0.1012215428},
{"learn":[0.8091591239],"iteration":678,"passed_time":3.123649549,"remaining_time":0.09660771802},
{"learn":[0.8090723302],"iteration":679,"passed_time":3.127321981,"remaining_time":0.09198005826},
{"learn":[0.8087791363],"iteration":680,"passed_time":3.13253252,"remaining_time":0.0873981173},
{"learn":[0.8086654434],"iteration":681,"passed_time":3.137148706,"remaining_time":0.0827986462},
{"learn":[0.808389785],"iteration":682,"passed_time":3.141954188,"remaining_time":0.07820383777},
{"learn":[0.8080914044],"iteration":683,"passed_time":3.146923471,"remaining_time":0.07361224493},
{"learn":[0.808006686],"iteration":684,"passed_time":3.151332088,"remaining_time":0.069007272},
{"learn":[0.8077880792],"iteration":685,"passed_time":3.155471338,"remaining_time":0.06439737424},
{"learn":[0.807387964],"iteration":686,"passed_time":3.15946403,"remaining_time":0.05978607335},
{"learn":[0.8072096185],"iteration":687,"passed_time":3.163556588,"remaining_time":0.05517831259},
{"learn":[0.807117453],"iteration":688,"passed_time":3.167958009,"remaining_time":0.05057697837},
{"learn":[0.80705082],"iteration":689,"passed_time":3.171818565,"remaining_time":0.045968385},
{"learn":[0.806786706],"iteration":690,"passed_time":3.175857372,"remaining_time":0.04136427836},
{"learn":[0.8067403515],"iteration":691,"passed_time":3.179656468,"remaining_time":0.03675903431},
{"learn":[0.8066200559],"iteration":692,"passed_time":3.183763459,"remaining_time":0.03215922686},
{"learn":[0.8065571295],"iteration":693,"passed_time":3.187412525,"remaining_time":0.02755688062},
{"learn":[0.8064373895],"iteration":694,"passed_time":3.191461768,"remaining_time":0.02296015661},
{"learn":[0.8062954951],"iteration":695,"passed_time":3.196151148,"remaining_time":0.01836868476},
{"learn":[0.8060715992],"iteration":696,"passed_time":3.200994328,"remaining_time":0.01377759395},
{"learn":[0.8058357749],"iteration":697,"passed_time":3.204877434,"remaining_time":0.009183029897},
{"learn":[0.8056836669],"iteration":698,"passed_time":3.208878138,"remaining_time":0.004590669726},
{"learn":[0.8054330466],"iteration":699,"passed_time":3.213071224,"remaining_time":0}
]}